PyHelpTools/__init__.py
PyHelpTools-0.1.1.dist-info/LICENSE
PyHelpTools-0.1.1.dist-info/METADATA
PyHelpTools-0.1.1.dist-info/WHEEL
PyHelpTools-0.1.1.dist-info/top_level.txt
PyHelpTools-0.1.1.dist-info/RECORD
