Metadata-Version: 2.1
Name: PyHelpTools
Version: 0.1.1
Summary: PyHelpTools are tools to help develepors
Home-page: https://github.com/Dashtiss/PyHelpTools
Author: Dashtiss
Author-email: dashtiss@gmail.com
License: UNKNOWN
Platform: UNKNOWN
Classifier: Programming Language :: Python :: 3
Classifier: License :: OSI Approved :: MIT License
Classifier: Operating System :: OS Independent
Requires-Python: >=3.6
